JsonDF/Data.py
JsonDF/__init__.py
JsonDF/utils/Dict/Dict.py
JsonDF/utils/Dict/__init__.py
JsonDF/utils/Json/Json.py
JsonDF/utils/Json/__init__.py
JsonDF/utils/List/List.py
JsonDF/utils/List/__init__.py
jsondf-1.1.1.dist-info/METADATA
jsondf-1.1.1.dist-info/WHEEL
jsondf-1.1.1.dist-info/licenses/LICENSE
jsondf-1.1.1.dist-info/RECORD
