Metadata-Version: 2.1
Name: JsonDF
Version: 1.1.1
Summary: A project for reading JSON data and parse it for DF, with ability to make you edits to Json, insert values, delete values, update values and search for any values.
Project-URL: Homepage, https://github.com/OsamaElsherif/JsonDF
Project-URL: Bug Tracker, https://github.com/OsamaElsherif/JsonDF/issues
Author-email: Osama Elsherif <elsherif.osama155@gmail.com>
License-File: LICENSE
Classifier: License :: OSI Approved :: MIT License
Classifier: Operating System :: OS Independent
Classifier: Programming Language :: Python :: 3
Requires-Python: >=3.8
